tccm_api/__init__.py
tccm_api/app.py
tccm_api/config.py
tccm_api/enums.py
tccm_api/namespaces.py
tccm_api/utils.py
tccm_api/db/__init__.py
tccm_api/db/cypher_queries.py
tccm_api/db/models.py
tccm_api/db/tccm_graph.py
tccm_api/loader/__init__.py
tccm_api/loader/base_loader.py
tccm_api/loader/ncit_flat_loader.py
tccm_api/loader/obo_loader.py
tccm_api/loader/onto_loader.py
tccm_api/routers/__init__.py
tccm_api/routers/code_set.py
tccm_api/routers/concept_reference.py
tccm_api/routers/concept_system.py
tccm_loader/__init__.py
tccm_loader/icdo.py
tccm_loader/ncit.py
tccm_loader/obo.py
tests/__init__.py
tests/conftest.py
tests/test_main.py
tests/test_utils.py
tccm_api-0.1.5.dist-info/LICENSE
tccm_api-0.1.5.dist-info/METADATA
tccm_api-0.1.5.dist-info/WHEEL
tccm_api-0.1.5.dist-info/top_level.txt
tccm_api-0.1.5.dist-info/RECORD
