Metadata-Version: 2.1
Name: tccm-api
Version: 0.1.5
Summary: TCCM rest api
Home-page: https://github.com/hot-ecosystem/tccm-api
Author: Dazhi Jiao
Author-email: djiao@jhu.edu
Maintainer: Dazhi Jiao
Maintainer-email: djiao@jhu.edu
License: CC0
Platform: UNKNOWN
License-File: LICENSE
Requires-Dist: aiofiles
Requires-Dist: biolinkml
Requires-Dist: fastapi
Requires-Dist: neo4j
Requires-Dist: owlready2
Requires-Dist: pandas
Requires-Dist: prefixcommons
Requires-Dist: pydantic
Requires-Dist: pyld
Requires-Dist: python-docx
Requires-Dist: python-dotenv
Requires-Dist: python-multipart
Requires-Dist: rdflib
Requires-Dist: rdflib-pyld-compat
Requires-Dist: rfc3986
Requires-Dist: uvicorn
